{
    "recommendationTrend": {
        "trend": [
            {
                "period": "0m",
                "strongBuy": 6,
                "buy": 15,
                "hold": 2,
                "sell": 0,
                "strongSell": 0
            },
            {
                "period": "-1m",
                "strongBuy": 6,
                "buy": 14,
                "hold": 2,
                "sell": 0,
                "strongSell": 1
            },
            {
                "period": "-2m",
                "strongBuy": 6,
                "buy": 14,
                "hold": 2,
                "sell": 1,
                "strongSell": 0
            },
            {
                "period": "-3m",
                "strongBuy": 6,
                "buy": 14,
                "hold": 2,
                "sell": 1,
                "strongSell": 0
            }
        ],
        "maxAge": 86400
    },
    "equityPerformance": {
        "maxAge": 1,
        "benchmark": {
            "symbol": "^GSPC",
            "shortName": "S&P 500"
        },
        "performanceOverview": {
            "asOfDate": {
                "raw": 1745366400,
                "fmt": "2025-04-23"
            },
            "fiveDaysReturn": {
                "raw": 0.025648732,
                "fmt": "2.56%"
            },
            "oneMonthReturn": {
                "raw": -0.12689964,
                "fmt": "-12.69%"
            },
            "threeMonthReturn": {
                "raw": -0.18169157,
                "fmt": "-18.17%"
            },
            "sixMonthReturn": {
                "raw": 0.04778299,
                "fmt": "4.78%"
            },
            "ytdReturnPct": {
                "raw": -0.030911965,
                "fmt": "-3.09%"
            },
            "oneYearTotalReturn": {
                "raw": 0.51599044,
                "fmt": "51.60%"
            },
            "twoYearTotalReturn": {
                "raw": 1.3842121,
                "fmt": "138.42%"
            },
            "threeYearTotalReturn": {
                "raw": 1.413911,
                "fmt": "141.39%"
            },
            "fiveYearTotalReturn": {
                "raw": 19.595016,
                "fmt": "1,959.50%"
            },
            "tenYearTotalReturn": {
                "raw": 1.6619779,
                "fmt": "166.20%"
            },
            "maxReturn": {
                "raw": 6.151452,
                "fmt": "615.15%"
            }
        },
        "performanceOverviewBenchmark": {
            "asOfDate": {
                "raw": 1745366400,
                "fmt": "2025-04-23"
            },
            "fiveDaysReturn": {
                "raw": -0.003848702,
                "fmt": "-0.38%"
            },
            "oneMonthReturn": {
                "raw": -0.05146839,
                "fmt": "-5.15%"
            },
            "threeMonthReturn": {
                "raw": -0.121406324,
                "fmt": "-12.14%"
            },
            "sixMonthReturn": {
                "raw": -0.07271512,
                "fmt": "-7.27%"
            },
            "ytdReturnPct": {
                "raw": -0.08599147,
                "fmt": "-8.60%"
            },
            "oneYearTotalReturn": {
                "raw": 0.06021242,
                "fmt": "6.02%"
            },
            "twoYearTotalReturn": {
                "raw": 0.30055252,
                "fmt": "30.06%"
            },
            "threeYearTotalReturn": {
                "raw": 0.25845903,
                "fmt": "25.85%"
            },
            "fiveYearTotalReturn": {
                "raw": 0.9214596,
                "fmt": "92.15%"
            },
            "tenYearTotalReturn": {
                "raw": 1.5442679,
                "fmt": "154.43%"
            },
            "maxReturn": {
                "raw": 303.4088,
                "fmt": "30,340.88%"
            }
        }
    },
    "quoteUnadjustedPerformanceOverview": {
        "maxAge": 1,
        "benchmark": {
            "symbol": "^GSPC",
            "shortName": "S&P 500"
        },
        "performanceOverview": {
            "asOfDate": {
                "raw": 1745366400,
                "fmt": "2025-04-23"
            },
            "fiveDaysReturn": {
                "raw": 0.025648732,
                "fmt": "2.56%"
            },
            "oneMonthReturn": {
                "raw": -0.12689964,
                "fmt": "-12.69%"
            },
            "threeMonthReturn": {
                "raw": -0.18468231,
                "fmt": "-18.47%"
            },
            "sixMonthReturn": {
                "raw": 0.039254762,
                "fmt": "3.93%"
            },
            "ytdReturnPct": {
                "raw": -0.034453746,
                "fmt": "-3.45%"
            },
            "oneYearTotalReturn": {
                "raw": 0.48564783,
                "fmt": "48.56%"
            },
            "twoYearTotalReturn": {
                "raw": 1.2794604,
                "fmt": "127.95%"
            },
            "threeYearTotalReturn": {
                "raw": 1.262702,
                "fmt": "126.27%"
            },
            "fiveYearTotalReturn": {
                "raw": 17.612312,
                "fmt": "1,761.23%"
            },
            "tenYearTotalReturn": {
                "raw": 0.6074427,
                "fmt": "60.74%"
            },
            "maxReturn": {
                "raw": 6.151452,
                "fmt": "615.15%"
            }
        },
        "performanceOverviewBenchmark": {
            "asOfDate": {
                "raw": 1745366400,
                "fmt": "2025-04-23"
            },
            "fiveDaysReturn": {
                "raw": -0.003848702,
                "fmt": "-0.38%"
            },
            "oneMonthReturn": {
                "raw": -0.05146839,
                "fmt": "-5.15%"
            },
            "threeMonthReturn": {
                "raw": -0.121406324,
                "fmt": "-12.14%"
            },
            "sixMonthReturn": {
                "raw": -0.07271512,
                "fmt": "-7.27%"
            },
            "ytdReturnPct": {
                "raw": -0.08599147,
                "fmt": "-8.60%"
            },
            "oneYearTotalReturn": {
                "raw": 0.06021242,
                "fmt": "6.02%"
            },
            "twoYearTotalReturn": {
                "raw": 0.30055252,
                "fmt": "30.06%"
            },
            "threeYearTotalReturn": {
                "raw": 0.25845903,
                "fmt": "25.85%"
            },
            "fiveYearTotalReturn": {
                "raw": 0.9214596,
                "fmt": "92.15%"
            },
            "tenYearTotalReturn": {
                "raw": 1.5442679,
                "fmt": "154.43%"
            },
            "maxReturn": {
                "raw": 303.4088,
                "fmt": "30,340.88%"
            }
        }
    },
    "esgScores": {
        "maxAge": 86400,
        "totalEsg": {
            "raw": 31.82,
            "fmt": "31.8"
        },
        "environmentScore": {
            "raw": 13.96,
            "fmt": "14.0"
        },
        "socialScore": {
            "raw": 15.07,
            "fmt": "15.1"
        },
        "governanceScore": {
            "raw": 2.79,
            "fmt": "2.8"
        },
        "ratingYear": 2025,
        "ratingMonth": 4,
        "highestControversy": 2.0,
        "peerCount": 84,
        "esgPerformance": "LEAD_PERF",
        "peerGroup": "Refiners & Pipelines",
        "relatedControversy": [
            "Operations Incidents"
        ],
        "peerEsgScorePerformance": {
            "min": 19.32,
            "avg": 34.196785714285724,
            "max": 54.42
        },
        "peerGovernancePerformance": {
            "min": 1.52,
            "avg": 3.896923076923076,
            "max": 6.16
        },
        "peerSocialPerformance": {
            "min": 6.17,
            "avg": 10.42871794871795,
            "max": 19.03
        },
        "peerEnvironmentPerformance": {
            "min": 7.87,
            "avg": 14.894102564102562,
            "max": 24.27
        },
        "peerHighestControversyPerformance": {
            "min": 0.0,
            "avg": 1.0476190476190477,
            "max": 4.0
        },
        "percentile": null,
        "environmentPercentile": null,
        "socialPercentile": null,
        "governancePercentile": null,
        "adult": false,
        "alcoholic": false,
        "animalTesting": false,
        "catholic": null,
        "controversialWeapons": false,
        "smallArms": false,
        "furLeather": false,
        "gambling": false,
        "gmo": false,
        "militaryContract": false,
        "nuclear": false,
        "pesticides": false,
        "palmOil": false,
        "coal": false,
        "tobacco": false
    },
    "defaultKeyStatistics": {
        "maxAge": 1,
        "priceHint": {
            "raw": 2,
            "fmt": "2",
            "longFmt": "2"
        },
        "enterpriseValue": {
            "raw": 53549400064,
            "fmt": "53.55B",
            "longFmt": "53,549,400,064"
        },
        "forwardPE": {
            "raw": 17.178793,
            "fmt": "17.18"
        },
        "profitMargins": {
            "raw": 0.08009,
            "fmt": "8.01%"
        },
        "floatShares": {
            "raw": 214551625,
            "fmt": "214.55M",
            "longFmt": "214,551,625"
        },
        "sharesOutstanding": {
            "raw": 217584992,
            "fmt": "217.58M",
            "longFmt": "217,584,992"
        },
        "sharesShort": {
            "raw": 4211360,
            "fmt": "4.21M",
            "longFmt": "4,211,360"
        },
        "sharesShortPriorMonth": {
            "raw": 3791641,
            "fmt": "3.79M",
            "longFmt": "3,791,641"
        },
        "sharesShortPreviousMonthDate": {
            "raw": 1740700800,
            "fmt": "2025-02-28"
        },
        "dateShortInterest": {
            "raw": 1743379200,
            "fmt": "2025-03-31"
        },
        "sharesPercentSharesOut": {
            "raw": 0.0194,
            "fmt": "1.94%"
        },
        "heldPercentInsiders": {
            "raw": 0.014090001,
            "fmt": "1.41%"
        },
        "heldPercentInstitutions": {
            "raw": 0.93245006,
            "fmt": "93.25%"
        },
        "shortRatio": {
            "raw": 2.3,
            "fmt": "2.3"
        },
        "shortPercentOfFloat": {
            "raw": 0.0224,
            "fmt": "2.24%"
        },
        "beta": {
            "raw": 1.745,
            "fmt": "1.75"
        },
        "impliedSharesOutstanding": {
            "raw": 222258000,
            "fmt": "222.26M",
            "longFmt": "222,258,000"
        },
        "morningStarOverallRating": {},
        "morningStarRiskRating": {},
        "category": null,
        "bookValue": {
            "raw": 11.905,
            "fmt": "11.90"
        },
        "priceToBook": {
            "raw": 14.477111,
            "fmt": "14.48"
        },
        "annualReportExpenseRatio": {},
        "ytdReturn": {},
        "qtdReturn": {},
        "beta3Year": {},
        "totalAssets": {},
        "yield": {},
        "fundFamily": null,
        "fundInceptionDate": {},
        "legalType": null,
        "threeYearAverageReturn": {},
        "fiveYearAverageReturn": {},
        "priceToSalesTrailing12Months": {},
        "lastFiscalYearEnd": {
            "raw": 1735603200,
            "fmt": "2024-12-31"
        },
        "nextFiscalYearEnd": {
            "raw": 1767139200,
            "fmt": "2025-12-31"
        },
        "mostRecentQuarter": {
            "raw": 1735603200,
            "fmt": "2024-12-31"
        },
        "earningsQuarterlyGrowth": {
            "raw": 0.172,
            "fmt": "17.20%"
        },
        "revenueQuarterlyGrowth": {},
        "netIncomeToCommon": {
            "raw": 1269500032,
            "fmt": "1.27B",
            "longFmt": "1,269,500,032"
        },
        "trailingEps": {
            "raw": 5.74,
            "fmt": "5.74"
        },
        "forwardEps": {
            "raw": 8.26,
            "fmt": "8.26"
        },
        "pegRatio": {},
        "lastSplitFactor": null,
        "lastSplitDate": {},
        "enterpriseToRevenue": {
            "raw": 3.269,
            "fmt": "3.27"
        },
        "enterpriseToEbitda": {
            "raw": 12.969,
            "fmt": "12.97"
        },
        "52WeekChange": {
            "raw": 0.45224333,
            "fmt": "45.22%"
        },
        "SandP52WeekChange": {
            "raw": 0.04740894,
            "fmt": "4.74%"
        },
        "lastDividendValue": {
            "raw": 0.75,
            "fmt": "0.75"
        },
        "lastDividendDate": {
            "raw": 1738281600,
            "fmt": "2025-01-31"
        },
        "lastCapGain": {},
        "annualHoldingsTurnover": {},
        "latestFundingDate": {},
        "latestAmountRaised": {},
        "latestImpliedValuation": {},
        "latestShareClass": null,
        "leadInvestor": null,
        "fundingToDate": {},
        "totalFundingRounds": {}
    },
    "summaryProfile": {
        "address1": "811 Louisiana Street",
        "address2": "Suite 2100",
        "city": "Houston",
        "state": "TX",
        "zip": "77002",
        "country": "United States",
        "phone": "713 584 1000",
        "fax": "713 584 1100",
        "website": "https://www.targaresources.com",
        "industry": "Oil & Gas Midstream",
        "industryKey": "oil-gas-midstream",
        "industryDisp": "Oil & Gas Midstream",
        "sector": "Energy",
        "sectorKey": "energy",
        "sectorDisp": "Energy",
        "longBusinessSummary": "Targa Resources Corp., together with its subsidiary, Targa Resources Partners LP, owns, operates, acquires, and develops a portfolio of complementary domestic infrastructure assets in North America. It operates in two segments, Gathering and Processing, and Logistics and Transportation. The company is involved in gathering, compressing, treating, processing, transporting, and selling natural gas; storing, fractionating, treating, transporting, and selling natural gas liquids (NGL) and NGL products, including services to liquefied petroleum gas exporters; and gathering, storing, terminaling, purchasing, and selling crude oil. It is also involved in the purchase and resale of NGL products; and sale of propane, as well as provision of related logistics services to multi-state retailers, independent retailers, and other end-users. In addition, the company offers NGL balancing services; and transportation services to refineries and petrochemical companies in the Gulf Coast area, as well as purchases, markets, and resells natural gas. As of December 31, 2024, it leased and managed approximately 531 railcars; 131 tractors; and 6 vacuum trucks and 2 pressurized NGL barges, as well as owns 8 tractors. Targa Resources Corp. was incorporated in 2005 and is headquartered in Houston, Texas.",
        "fullTimeEmployees": 3370,
        "companyOfficers": [],
        "executiveTeam": [],
        "maxAge": 86400
    },
    "financialsTemplate": {
        "code": "U",
        "maxAge": 1
    },
    "summaryDetail": {
        "maxAge": 1,
        "priceHint": {
            "raw": 2,
            "fmt": "2",
            "longFmt": "2"
        },
        "previousClose": {
            "raw": 170.9,
            "fmt": "170.90"
        },
        "open": {
            "raw": 175.55,
            "fmt": "175.55"
        },
        "dayLow": {
            "raw": 170.605,
            "fmt": "170.60"
        },
        "dayHigh": {
            "raw": 178.28,
            "fmt": "178.28"
        },
        "regularMarketPreviousClose": {
            "raw": 170.9,
            "fmt": "170.90"
        },
        "regularMarketOpen": {
            "raw": 175.55,
            "fmt": "175.55"
        },
        "regularMarketDayLow": {
            "raw": 170.605,
            "fmt": "170.60"
        },
        "regularMarketDayHigh": {
            "raw": 178.28,
            "fmt": "178.28"
        },
        "dividendRate": {
            "raw": 4.0,
            "fmt": "4.00"
        },
        "dividendYield": {
            "raw": 0.0232,
            "fmt": "2.32%"
        },
        "exDividendDate": {
            "raw": 1745971200,
            "fmt": "2025-04-30"
        },
        "payoutRatio": {
            "raw": 0.4791,
            "fmt": "47.91%"
        },
        "fiveYearAvgDividendYield": {
            "raw": 3.12,
            "fmt": "3.12"
        },
        "beta": {
            "raw": 1.745,
            "fmt": "1.75"
        },
        "trailingPE": {
            "raw": 30.026134,
            "fmt": "30.03"
        },
        "forwardPE": {
            "raw": 20.865618,
            "fmt": "20.87"
        },
        "volume": {
            "raw": 2237624,
            "fmt": "2.24M",
            "longFmt": "2,237,624"
        },
        "regularMarketVolume": {
            "raw": 2237624,
            "fmt": "2.24M",
            "longFmt": "2,237,624"
        },
        "averageVolume": {
            "raw": 2038838,
            "fmt": "2.04M",
            "longFmt": "2,038,838"
        },
        "averageVolume10days": {
            "raw": 2782420,
            "fmt": "2.78M",
            "longFmt": "2,782,420"
        },
        "averageDailyVolume10Day": {
            "raw": 2782420,
            "fmt": "2.78M",
            "longFmt": "2,782,420"
        },
        "bid": {
            "raw": 0.0,
            "fmt": "0.00"
        },
        "ask": {
            "raw": 0.0,
            "fmt": "0.00"
        },
        "bidSize": {
            "raw": 800,
            "fmt": "800",
            "longFmt": "800"
        },
        "askSize": {
            "raw": 800,
            "fmt": "800",
            "longFmt": "800"
        },
        "marketCap": {
            "raw": 37500776448,
            "fmt": "37.5B",
            "longFmt": "37,500,776,448"
        },
        "yield": {},
        "ytdReturn": {},
        "qtdReturn": {},
        "totalAssets": {},
        "expireDate": {},
        "strikePrice": {},
        "openInterest": {},
        "fiftyTwoWeekLow": {
            "raw": 110.09,
            "fmt": "110.09"
        },
        "fiftyTwoWeekHigh": {
            "raw": 218.51,
            "fmt": "218.51"
        },
        "priceToSalesTrailing12Months": {
            "raw": 2.289215,
            "fmt": "2.29"
        },
        "fiftyDayAverage": {
            "raw": 189.5604,
            "fmt": "189.56"
        },
        "twoHundredDayAverage": {
            "raw": 172.93295,
            "fmt": "172.93"
        },
        "trailingAnnualDividendRate": {
            "raw": 3.0,
            "fmt": "3.00"
        },
        "trailingAnnualDividendYield": {
            "raw": 0.017554127,
            "fmt": "1.76%"
        },
        "navPrice": {},
        "currency": "USD",
        "fromCurrency": null,
        "toCurrency": null,
        "lastMarket": null,
        "coinMarketCapLink": null,
        "volume24Hr": {},
        "volumeAllCurrencies": {},
        "circulatingSupply": {},
        "algorithm": null,
        "maxSupply": {},
        "startDate": {},
        "tradeable": false
    },
    "earnings": {
        "maxAge": 86400,
        "earningsChart": {
            "quarterly": [
                {
                    "date": "1Q2024",
                    "actual": {
                        "raw": 1.3734,
                        "fmt": "1.37"
                    },
                    "estimate": {
                        "raw": 1.27554,
                        "fmt": "1.28"
                    }
                },
                {
                    "date": "2Q2024",
                    "actual": {
                        "raw": 1.5779,
                        "fmt": "1.58"
                    },
                    "estimate": {
                        "raw": 1.26651,
                        "fmt": "1.27"
                    }
                },
                {
                    "date": "3Q2024",
                    "actual": {
                        "raw": 1.9231,
                        "fmt": "1.92"
                    },
                    "estimate": {
                        "raw": 1.61433,
                        "fmt": "1.61"
                    }
                },
                {
                    "date": "4Q2024",
                    "actual": {
                        "raw": 1.8173,
                        "fmt": "1.82"
                    },
                    "estimate": {
                        "raw": 1.82927,
                        "fmt": "1.83"
                    }
                }
            ],
            "currentQuarterEstimate": {
                "raw": 2.08056,
                "fmt": "2.08"
            },
            "currentQuarterEstimateDate": "1Q",
            "currentQuarterEstimateYear": 2025,
            "earningsDate": [
                {
                    "raw": 1746102600,
                    "fmt": "2025-05-01"
                }
            ],
            "isEarningsDateEstimate": false
        },
        "financialsChart": {
            "yearly": [
                {
                    "date": 2021,
                    "revenue": {
                        "raw": 16949800000,
                        "fmt": "16.95B",
                        "longFmt": "16,949,800,000"
                    },
                    "earnings": {
                        "raw": 446867000,
                        "fmt": "446.87M",
                        "longFmt": "446,867,000"
                    }
                },
                {
                    "date": 2022,
                    "revenue": {
                        "raw": 20929800000,
                        "fmt": "20.93B",
                        "longFmt": "20,929,800,000"
                    },
                    "earnings": {
                        "raw": 894774300,
                        "fmt": "894.77M",
                        "longFmt": "894,774,300"
                    }
                },
                {
                    "date": 2023,
                    "revenue": {
                        "raw": 16060300000,
                        "fmt": "16.06B",
                        "longFmt": "16,060,300,000"
                    },
                    "earnings": {
                        "raw": 679049000,
                        "fmt": "679.05M",
                        "longFmt": "679,049,000"
                    }
                },
                {
                    "date": 2024,
                    "revenue": {
                        "raw": 16381500000,
                        "fmt": "16.38B",
                        "longFmt": "16,381,500,000"
                    },
                    "earnings": {
                        "raw": 1480862600,
                        "fmt": "1.48B",
                        "longFmt": "1,480,862,600"
                    }
                }
            ],
            "quarterly": [
                {
                    "date": "1Q2024",
                    "revenue": {
                        "raw": 4562400000,
                        "fmt": "4.56B",
                        "longFmt": "4,562,400,000"
                    },
                    "earnings": {
                        "raw": 307234700,
                        "fmt": "307.23M",
                        "longFmt": "307,234,700"
                    }
                },
                {
                    "date": "2Q2024",
                    "revenue": {
                        "raw": 3562000000,
                        "fmt": "3.56B",
                        "longFmt": "3,562,000,000"
                    },
                    "earnings": {
                        "raw": 350133500,
                        "fmt": "350.13M",
                        "longFmt": "350,133,500"
                    }
                },
                {
                    "date": "3Q2024",
                    "revenue": {
                        "raw": 3851800000,
                        "fmt": "3.85B",
                        "longFmt": "3,851,800,000"
                    },
                    "earnings": {
                        "raw": 423077000,
                        "fmt": "423.08M",
                        "longFmt": "423,077,000"
                    }
                },
                {
                    "date": "4Q2024",
                    "revenue": {
                        "raw": 4405200000,
                        "fmt": "4.41B",
                        "longFmt": "4,405,200,000"
                    },
                    "earnings": {
                        "raw": 399400300,
                        "fmt": "399.4M",
                        "longFmt": "399,400,300"
                    }
                }
            ]
        },
        "financialCurrency": "USD"
    },
    "calendarEvents": {
        "maxAge": 1,
        "earnings": {
            "earningsDate": [
                {
                    "raw": 1746102600,
                    "fmt": "2025-05-01"
                }
            ],
            "earningsCallDate": [
                {
                    "raw": 1746111600,
                    "fmt": "2025-05-01"
                }
            ],
            "isEarningsDateEstimate": false,
            "earningsAverage": {
                "raw": 2.08056,
                "fmt": "2.08"
            },
            "earningsLow": {
                "raw": 1.97,
                "fmt": "1.97"
            },
            "earningsHigh": {
                "raw": 2.27286,
                "fmt": "2.27"
            },
            "revenueAverage": {
                "raw": 5036982690,
                "fmt": "5.04B",
                "longFmt": "5,036,982,690"
            },
            "revenueLow": {
                "raw": 4346653000,
                "fmt": "4.35B",
                "longFmt": "4,346,653,000"
            },
            "revenueHigh": {
                "raw": 5982376060,
                "fmt": "5.98B",
                "longFmt": "5,982,376,060"
            }
        },
        "exDividendDate": {
            "raw": 1745971200,
            "fmt": "2025-04-30"
        },
        "dividendDate": {
            "raw": 1747267200,
            "fmt": "2025-05-15"
        }
    },
    "pageViews": {
        "shortTermTrend": "DOWN",
        "midTermTrend": "UP",
        "longTermTrend": "UP",
        "maxAge": 1
    },
    "price": {
        "maxAge": 1,
        "preMarketChange": {},
        "preMarketPrice": {},
        "preMarketSource": "DELAYED",
        "postMarketChangePercent": {
            "raw": 0.0,
            "fmt": "0.00%"
        },
        "postMarketChange": {
            "raw": 0.0,
            "fmt": "0.00"
        },
        "postMarketTime": 1745445958,
        "postMarketPrice": {
            "raw": 172.35,
            "fmt": "172.35"
        },
        "postMarketSource": "DELAYED",
        "regularMarketChangePercent": {
            "raw": 0.008484569,
            "fmt": "0.85%"
        },
        "regularMarketChange": {
            "raw": 1.45001,
            "fmt": "1.45"
        },
        "regularMarketTime": 1745438406,
        "priceHint": {
            "raw": 2,
            "fmt": "2",
            "longFmt": "2"
        },
        "regularMarketPrice": {
            "raw": 172.35,
            "fmt": "172.35"
        },
        "regularMarketDayHigh": {
            "raw": 178.28,
            "fmt": "178.28"
        },
        "regularMarketDayLow": {
            "raw": 170.605,
            "fmt": "170.60"
        },
        "regularMarketVolume": {
            "raw": 2237624,
            "fmt": "2.24M",
            "longFmt": "2,237,624.00"
        },
        "averageDailyVolume10Day": {
            "raw": 2782420,
            "fmt": "2.78M",
            "longFmt": "2,782,420"
        },
        "averageDailyVolume3Month": {
            "raw": 2038838,
            "fmt": "2.04M",
            "longFmt": "2,038,838"
        },
        "regularMarketPreviousClose": {
            "raw": 170.9,
            "fmt": "170.90"
        },
        "regularMarketSource": "FREE_REALTIME",
        "regularMarketOpen": {
            "raw": 175.55,
            "fmt": "175.55"
        },
        "strikePrice": {},
        "openInterest": {},
        "exchange": "NYQ",
        "exchangeName": "NYSE",
        "exchangeDataDelayedBy": 0,
        "marketState": "PREPRE",
        "quoteType": "EQUITY",
        "symbol": "TRGP",
        "underlyingSymbol": null,
        "shortName": "Targa Resources, Inc.",
        "longName": "Targa Resources Corp.",
        "currency": "USD",
        "quoteSourceName": "Delayed Quote",
        "currencySymbol": "$",
        "fromCurrency": null,
        "toCurrency": null,
        "lastMarket": null,
        "volume24Hr": {},
        "volumeAllCurrencies": {},
        "circulatingSupply": {},
        "marketCap": {
            "raw": 37500776448,
            "fmt": "37.50B",
            "longFmt": "37,500,776,448.00"
        }
    },
    "corporateActions": {
        "corporateActions": [
            {
                "header": "Dividend",
                "message": "TRGP announced a cash dividend of 1.00 with an ex-date of Apr. 30, 2025",
                "meta": {
                    "eventType": "DIVIDEND",
                    "dateEpochMs": 1745985600000,
                    "amount": "1.00"
                }
            }
        ],
        "maxAge": 1
    },
    "financialData": {
        "maxAge": 86400,
        "currentPrice": {
            "raw": 172.35,
            "fmt": "172.35"
        },
        "targetHighPrice": {
            "raw": 259.0,
            "fmt": "259.00"
        },
        "targetLowPrice": {
            "raw": 157.0,
            "fmt": "157.00"
        },
        "targetMeanPrice": {
            "raw": 215.02956,
            "fmt": "215.03"
        },
        "targetMedianPrice": {
            "raw": 219.675,
            "fmt": "219.68"
        },
        "recommendationMean": {
            "raw": 1.43478,
            "fmt": "1.43"
        },
        "recommendationKey": "strong_buy",
        "numberOfAnalystOpinions": {
            "raw": 22,
            "fmt": "22",
            "longFmt": "22"
        },
        "totalCash": {
            "raw": 157300000,
            "fmt": "157.3M",
            "longFmt": "157,300,000"
        },
        "totalCashPerShare": {
            "raw": 0.721,
            "fmt": "0.72"
        },
        "ebitda": {
            "raw": 4128999936,
            "fmt": "4.13B",
            "longFmt": "4,128,999,936"
        },
        "totalDebt": {
            "raw": 14290199552,
            "fmt": "14.29B",
            "longFmt": "14,290,199,552"
        },
        "quickRatio": {
            "raw": 0.56,
            "fmt": "0.56"
        },
        "currentRatio": {
            "raw": 0.724,
            "fmt": "0.72"
        },
        "totalRevenue": {
            "raw": 16381500416,
            "fmt": "16.38B",
            "longFmt": "16,381,500,416"
        },
        "debtToEquity": {
            "raw": 323.439,
            "fmt": "323.44%"
        },
        "revenuePerShare": {
            "raw": 74.394,
            "fmt": "74.39"
        },
        "returnOnAssets": {
            "raw": 0.07762,
            "fmt": "7.76%"
        },
        "returnOnEquity": {
            "raw": 0.34414002,
            "fmt": "34.41%"
        },
        "grossProfits": {
            "raw": 5678499840,
            "fmt": "5.68B",
            "longFmt": "5,678,499,840"
        },
        "freeCashflow": {
            "raw": 291324992,
            "fmt": "291.32M",
            "longFmt": "291,324,992"
        },
        "operatingCashflow": {
            "raw": 3649700096,
            "fmt": "3.65B",
            "longFmt": "3,649,700,096"
        },
        "earningsGrowth": {
            "raw": 0.168,
            "fmt": "16.80%"
        },
        "revenueGrowth": {
            "raw": 0.039,
            "fmt": "3.90%"
        },
        "grossMargins": {
            "raw": 0.34664002,
            "fmt": "34.66%"
        },
        "ebitdaMargins": {
            "raw": 0.25205,
            "fmt": "25.21%"
        },
        "operatingMargins": {
            "raw": 0.15901,
            "fmt": "15.90%"
        },
        "profitMargins": {
            "raw": 0.08009,
            "fmt": "8.01%"
        },
        "financialCurrency": "USD"
    }
}