{
    "recommendationTrend": {
        "trend": [
            {
                "period": "0m",
                "strongBuy": 7,
                "buy": 11,
                "hold": 9,
                "sell": 0,
                "strongSell": 0
            },
            {
                "period": "-1m",
                "strongBuy": 8,
                "buy": 13,
                "hold": 10,
                "sell": 0,
                "strongSell": 0
            },
            {
                "period": "-2m",
                "strongBuy": 8,
                "buy": 13,
                "hold": 10,
                "sell": 0,
                "strongSell": 0
            },
            {
                "period": "-3m",
                "strongBuy": 8,
                "buy": 13,
                "hold": 10,
                "sell": 0,
                "strongSell": 0
            }
        ],
        "maxAge": 86400
    },
    "equityPerformance": {
        "maxAge": 1,
        "benchmark": {
            "symbol": "^GSPC",
            "shortName": "S&P 500"
        },
        "performanceOverview": {
            "asOfDate": {
                "raw": 1745366400,
                "fmt": "2025-04-23"
            },
            "fiveDaysReturn": {
                "raw": 0.08937957,
                "fmt": "8.94%"
            },
            "oneMonthReturn": {
                "raw": -0.140249,
                "fmt": "-14.02%"
            },
            "threeMonthReturn": {
                "raw": -0.14122553,
                "fmt": "-14.12%"
            },
            "sixMonthReturn": {
                "raw": -0.20259647,
                "fmt": "-20.26%"
            },
            "ytdReturnPct": {
                "raw": -0.04361957,
                "fmt": "-4.36%"
            },
            "oneYearTotalReturn": {
                "raw": -0.3893615,
                "fmt": "-38.94%"
            },
            "twoYearTotalReturn": {
                "raw": -0.37010983,
                "fmt": "-37.01%"
            },
            "threeYearTotalReturn": {
                "raw": -0.37066764,
                "fmt": "-37.07%"
            },
            "fiveYearTotalReturn": {
                "raw": 2.9231188,
                "fmt": "292.31%"
            },
            "tenYearTotalReturn": {
                "raw": -0.3282647,
                "fmt": "-32.83%"
            },
            "maxReturn": {
                "raw": 8.375602,
                "fmt": "837.56%"
            }
        },
        "performanceOverviewBenchmark": {
            "asOfDate": {
                "raw": 1745366400,
                "fmt": "2025-04-23"
            },
            "fiveDaysReturn": {
                "raw": -0.003848702,
                "fmt": "-0.38%"
            },
            "oneMonthReturn": {
                "raw": -0.05146839,
                "fmt": "-5.15%"
            },
            "threeMonthReturn": {
                "raw": -0.121406324,
                "fmt": "-12.14%"
            },
            "sixMonthReturn": {
                "raw": -0.07271512,
                "fmt": "-7.27%"
            },
            "ytdReturnPct": {
                "raw": -0.08599147,
                "fmt": "-8.60%"
            },
            "oneYearTotalReturn": {
                "raw": 0.06021242,
                "fmt": "6.02%"
            },
            "twoYearTotalReturn": {
                "raw": 0.30055252,
                "fmt": "30.06%"
            },
            "threeYearTotalReturn": {
                "raw": 0.25845903,
                "fmt": "25.85%"
            },
            "fiveYearTotalReturn": {
                "raw": 0.9214596,
                "fmt": "92.15%"
            },
            "tenYearTotalReturn": {
                "raw": 1.5442679,
                "fmt": "154.43%"
            },
            "maxReturn": {
                "raw": 303.4088,
                "fmt": "30,340.88%"
            }
        }
    },
    "quoteUnadjustedPerformanceOverview": {
        "maxAge": 1,
        "benchmark": {
            "symbol": "^GSPC",
            "shortName": "S&P 500"
        },
        "performanceOverview": {
            "asOfDate": {
                "raw": 1745366400,
                "fmt": "2025-04-23"
            },
            "fiveDaysReturn": {
                "raw": 0.08937957,
                "fmt": "8.94%"
            },
            "oneMonthReturn": {
                "raw": -0.140249,
                "fmt": "-14.02%"
            },
            "threeMonthReturn": {
                "raw": -0.14732513,
                "fmt": "-14.73%"
            },
            "sixMonthReturn": {
                "raw": -0.21336368,
                "fmt": "-21.34%"
            },
            "ytdReturnPct": {
                "raw": -0.050412454,
                "fmt": "-5.04%"
            },
            "oneYearTotalReturn": {
                "raw": -0.4087883,
                "fmt": "-40.88%"
            },
            "twoYearTotalReturn": {
                "raw": -0.42047364,
                "fmt": "-42.05%"
            },
            "threeYearTotalReturn": {
                "raw": -0.46478388,
                "fmt": "-46.48%"
            },
            "fiveYearTotalReturn": {
                "raw": 1.9403974,
                "fmt": "194.04%"
            },
            "tenYearTotalReturn": {
                "raw": -0.5312217,
                "fmt": "-53.12%"
            },
            "maxReturn": {
                "raw": 4.5253334,
                "fmt": "452.53%"
            }
        },
        "performanceOverviewBenchmark": {
            "asOfDate": {
                "raw": 1745366400,
                "fmt": "2025-04-23"
            },
            "fiveDaysReturn": {
                "raw": -0.003848702,
                "fmt": "-0.38%"
            },
            "oneMonthReturn": {
                "raw": -0.05146839,
                "fmt": "-5.15%"
            },
            "threeMonthReturn": {
                "raw": -0.121406324,
                "fmt": "-12.14%"
            },
            "sixMonthReturn": {
                "raw": -0.07271512,
                "fmt": "-7.27%"
            },
            "ytdReturnPct": {
                "raw": -0.08599147,
                "fmt": "-8.60%"
            },
            "oneYearTotalReturn": {
                "raw": 0.06021242,
                "fmt": "6.02%"
            },
            "twoYearTotalReturn": {
                "raw": 0.30055252,
                "fmt": "30.06%"
            },
            "threeYearTotalReturn": {
                "raw": 0.25845903,
                "fmt": "25.85%"
            },
            "fiveYearTotalReturn": {
                "raw": 0.9214596,
                "fmt": "92.15%"
            },
            "tenYearTotalReturn": {
                "raw": 1.5442679,
                "fmt": "154.43%"
            },
            "maxReturn": {
                "raw": 303.4088,
                "fmt": "30,340.88%"
            }
        }
    },
    "esgScores": {
        "maxAge": 86400,
        "totalEsg": {
            "raw": 31.55,
            "fmt": "31.5"
        },
        "environmentScore": {
            "raw": 17.4,
            "fmt": "17.4"
        },
        "socialScore": {
            "raw": 8.04,
            "fmt": "8.0"
        },
        "governanceScore": {
            "raw": 6.12,
            "fmt": "6.1"
        },
        "ratingYear": 2025,
        "ratingMonth": 4,
        "highestControversy": 2.0,
        "peerCount": 166,
        "esgPerformance": "LEAD_PERF",
        "peerGroup": "Oil & Gas Producers",
        "relatedControversy": [
            "Product & Service Incidents;Customer Incidents"
        ],
        "peerEsgScorePerformance": {
            "min": 7.23,
            "avg": 42.68060240963856,
            "max": 66.37
        },
        "peerGovernancePerformance": {
            "min": 3.03,
            "avg": 6.5938823529411765,
            "max": 13.27
        },
        "peerSocialPerformance": {
            "min": 1.61,
            "avg": 9.901529411764711,
            "max": 18.86
        },
        "peerEnvironmentPerformance": {
            "min": 0.08,
            "avg": 21.494823529411775,
            "max": 34.82
        },
        "peerHighestControversyPerformance": {
            "min": 0.0,
            "avg": 1.1506024096385543,
            "max": 5.0
        },
        "percentile": null,
        "environmentPercentile": null,
        "socialPercentile": null,
        "governancePercentile": null,
        "adult": false,
        "alcoholic": false,
        "animalTesting": false,
        "catholic": null,
        "controversialWeapons": false,
        "smallArms": false,
        "furLeather": false,
        "gambling": false,
        "gmo": false,
        "militaryContract": false,
        "nuclear": false,
        "pesticides": false,
        "palmOil": false,
        "coal": false,
        "tobacco": false
    },
    "defaultKeyStatistics": {
        "maxAge": 1,
        "priceHint": {
            "raw": 2,
            "fmt": "2",
            "longFmt": "2"
        },
        "enterpriseValue": {
            "raw": 28810065920,
            "fmt": "28.81B",
            "longFmt": "28,810,065,920"
        },
        "forwardPE": {
            "raw": 6.972049,
            "fmt": "6.97"
        },
        "profitMargins": {
            "raw": 0.19056,
            "fmt": "19.06%"
        },
        "floatShares": {
            "raw": 643456616,
            "fmt": "643.46M",
            "longFmt": "643,456,616"
        },
        "sharesOutstanding": {
            "raw": 648553984,
            "fmt": "648.55M",
            "longFmt": "648,553,984"
        },
        "sharesShort": {
            "raw": 16434214,
            "fmt": "16.43M",
            "longFmt": "16,434,214"
        },
        "sharesShortPriorMonth": {
            "raw": 17918441,
            "fmt": "17.92M",
            "longFmt": "17,918,441"
        },
        "sharesShortPreviousMonthDate": {
            "raw": 1740700800,
            "fmt": "2025-02-28"
        },
        "dateShortInterest": {
            "raw": 1743379200,
            "fmt": "2025-03-31"
        },
        "sharesPercentSharesOut": {
            "raw": 0.0253,
            "fmt": "2.53%"
        },
        "heldPercentInsiders": {
            "raw": 0.00775,
            "fmt": "0.77%"
        },
        "heldPercentInstitutions": {
            "raw": 0.78875,
            "fmt": "78.87%"
        },
        "shortRatio": {
            "raw": 1.84,
            "fmt": "1.84"
        },
        "shortPercentOfFloat": {
            "raw": 0.028800001,
            "fmt": "2.88%"
        },
        "beta": {
            "raw": 1.549,
            "fmt": "1.55"
        },
        "impliedSharesOutstanding": {
            "raw": 651057984,
            "fmt": "651.06M",
            "longFmt": "651,057,984"
        },
        "morningStarOverallRating": {},
        "morningStarRiskRating": {},
        "category": null,
        "bookValue": {
            "raw": 22.267,
            "fmt": "22.27"
        },
        "priceToBook": {
            "raw": 1.3957875,
            "fmt": "1.40"
        },
        "annualReportExpenseRatio": {},
        "ytdReturn": {},
        "qtdReturn": {},
        "beta3Year": {},
        "totalAssets": {},
        "yield": {},
        "fundFamily": null,
        "fundInceptionDate": {},
        "legalType": null,
        "threeYearAverageReturn": {},
        "fiveYearAverageReturn": {},
        "priceToSalesTrailing12Months": {},
        "lastFiscalYearEnd": {
            "raw": 1735603200,
            "fmt": "2024-12-31"
        },
        "nextFiscalYearEnd": {
            "raw": 1767139200,
            "fmt": "2025-12-31"
        },
        "mostRecentQuarter": {
            "raw": 1735603200,
            "fmt": "2024-12-31"
        },
        "earningsQuarterlyGrowth": {
            "raw": -0.445,
            "fmt": "-44.50%"
        },
        "revenueQuarterlyGrowth": {},
        "netIncomeToCommon": {
            "raw": 2891000064,
            "fmt": "2.89B",
            "longFmt": "2,891,000,064"
        },
        "trailingEps": {
            "raw": 4.56,
            "fmt": "4.56"
        },
        "forwardEps": {
            "raw": 4.46,
            "fmt": "4.46"
        },
        "pegRatio": {},
        "lastSplitFactor": "2:1",
        "lastSplitDate": {
            "raw": 1100563200,
            "fmt": "2004-11-16"
        },
        "enterpriseToRevenue": {
            "raw": 1.899,
            "fmt": "1.90"
        },
        "enterpriseToEbitda": {
            "raw": 3.899,
            "fmt": "3.90"
        },
        "52WeekChange": {
            "raw": -0.40695685,
            "fmt": "-40.70%"
        },
        "SandP52WeekChange": {
            "raw": 0.04740894,
            "fmt": "4.74%"
        },
        "lastDividendValue": {
            "raw": 0.24,
            "fmt": "0.24"
        },
        "lastDividendDate": {
            "raw": 1741910400,
            "fmt": "2025-03-14"
        },
        "lastCapGain": {},
        "annualHoldingsTurnover": {},
        "latestFundingDate": {},
        "latestAmountRaised": {},
        "latestImpliedValuation": {},
        "latestShareClass": null,
        "leadInvestor": null,
        "fundingToDate": {},
        "totalFundingRounds": {}
    },
    "summaryProfile": {
        "address1": "333 West Sheridan Avenue",
        "city": "Oklahoma City",
        "state": "OK",
        "zip": "73102-5015",
        "country": "United States",
        "phone": "405 235 3611",
        "website": "https://www.devonenergy.com",
        "industry": "Oil & Gas E&P",
        "industryKey": "oil-gas-e-p",
        "industryDisp": "Oil & Gas E&P",
        "sector": "Energy",
        "sectorKey": "energy",
        "sectorDisp": "Energy",
        "longBusinessSummary": "Devon Energy Corporation, an independent energy company, engages in the exploration, development, and production of oil, natural gas, and natural gas liquids in the United States. It operates in Delaware Basin located in southeast New Mexico and west Texas, Eagle Ford located in North America, Anadarko Basin located in western Oklahoma, Williston Basin located in North Dakota, and Powder River Basin located in Wyoming. Devon Energy Corporation was founded in 1971 and is headquartered in Oklahoma City, Oklahoma.",
        "fullTimeEmployees": 2300,
        "companyOfficers": [],
        "irWebsite": "http://phx.corporate-ir.net/phoenix.zhtml?c=67097&p=irol-irhome",
        "executiveTeam": [],
        "maxAge": 86400
    },
    "financialsTemplate": {
        "code": "M",
        "maxAge": 1
    },
    "summaryDetail": {
        "maxAge": 1,
        "priceHint": {
            "raw": 2,
            "fmt": "2",
            "longFmt": "2"
        },
        "previousClose": {
            "raw": 31.2,
            "fmt": "31.20"
        },
        "open": {
            "raw": 31.74,
            "fmt": "31.74"
        },
        "dayLow": {
            "raw": 30.71,
            "fmt": "30.71"
        },
        "dayHigh": {
            "raw": 32.31,
            "fmt": "32.31"
        },
        "regularMarketPreviousClose": {
            "raw": 31.2,
            "fmt": "31.20"
        },
        "regularMarketOpen": {
            "raw": 31.74,
            "fmt": "31.74"
        },
        "regularMarketDayLow": {
            "raw": 30.71,
            "fmt": "30.71"
        },
        "regularMarketDayHigh": {
            "raw": 32.31,
            "fmt": "32.31"
        },
        "dividendRate": {
            "raw": 0.96,
            "fmt": "0.96"
        },
        "dividendYield": {
            "raw": 0.0309,
            "fmt": "3.09%"
        },
        "exDividendDate": {
            "raw": 1741910400,
            "fmt": "2025-03-14"
        },
        "payoutRatio": {
            "raw": 0.318,
            "fmt": "31.80%"
        },
        "fiveYearAvgDividendYield": {
            "raw": 5.15,
            "fmt": "5.15"
        },
        "beta": {
            "raw": 1.549,
            "fmt": "1.55"
        },
        "trailingPE": {
            "raw": 6.8157897,
            "fmt": "6.82"
        },
        "forwardPE": {
            "raw": 6.96861,
            "fmt": "6.97"
        },
        "volume": {
            "raw": 8068172,
            "fmt": "8.07M",
            "longFmt": "8,068,172"
        },
        "regularMarketVolume": {
            "raw": 8068172,
            "fmt": "8.07M",
            "longFmt": "8,068,172"
        },
        "averageVolume": {
            "raw": 10138278,
            "fmt": "10.14M",
            "longFmt": "10,138,278"
        },
        "averageVolume10days": {
            "raw": 13249840,
            "fmt": "13.25M",
            "longFmt": "13,249,840"
        },
        "averageDailyVolume10Day": {
            "raw": 13249840,
            "fmt": "13.25M",
            "longFmt": "13,249,840"
        },
        "bid": {
            "raw": 0.0,
            "fmt": "0.00"
        },
        "ask": {
            "raw": 0.0,
            "fmt": "0.00"
        },
        "bidSize": {
            "raw": 1800,
            "fmt": "1.8k",
            "longFmt": "1,800"
        },
        "askSize": {
            "raw": 800,
            "fmt": "800",
            "longFmt": "800"
        },
        "marketCap": {
            "raw": 20157057024,
            "fmt": "20.16B",
            "longFmt": "20,157,057,024"
        },
        "yield": {},
        "ytdReturn": {},
        "qtdReturn": {},
        "totalAssets": {},
        "expireDate": {},
        "strikePrice": {},
        "openInterest": {},
        "fiftyTwoWeekLow": {
            "raw": 25.89,
            "fmt": "25.89"
        },
        "fiftyTwoWeekHigh": {
            "raw": 53.2,
            "fmt": "53.20"
        },
        "priceToSalesTrailing12Months": {
            "raw": 1.328657,
            "fmt": "1.33"
        },
        "fiftyDayAverage": {
            "raw": 34.0656,
            "fmt": "34.07"
        },
        "twoHundredDayAverage": {
            "raw": 38.3625,
            "fmt": "38.36"
        },
        "trailingAnnualDividendRate": {
            "raw": 1.45,
            "fmt": "1.45"
        },
        "trailingAnnualDividendYield": {
            "raw": 0.04647436,
            "fmt": "4.65%"
        },
        "navPrice": {},
        "currency": "USD",
        "fromCurrency": null,
        "toCurrency": null,
        "lastMarket": null,
        "coinMarketCapLink": null,
        "volume24Hr": {},
        "volumeAllCurrencies": {},
        "circulatingSupply": {},
        "algorithm": null,
        "maxSupply": {},
        "startDate": {},
        "tradeable": false
    },
    "earnings": {
        "maxAge": 86400,
        "earningsChart": {
            "quarterly": [
                {
                    "date": "1Q2024",
                    "actual": {
                        "raw": 1.16,
                        "fmt": "1.16"
                    },
                    "estimate": {
                        "raw": 1.11357,
                        "fmt": "1.11"
                    }
                },
                {
                    "date": "2Q2024",
                    "actual": {
                        "raw": 1.41,
                        "fmt": "1.41"
                    },
                    "estimate": {
                        "raw": 1.26745,
                        "fmt": "1.27"
                    }
                },
                {
                    "date": "3Q2024",
                    "actual": {
                        "raw": 1.1,
                        "fmt": "1.10"
                    },
                    "estimate": {
                        "raw": 1.09568,
                        "fmt": "1.10"
                    }
                },
                {
                    "date": "4Q2024",
                    "actual": {
                        "raw": 1.16,
                        "fmt": "1.16"
                    },
                    "estimate": {
                        "raw": 1.00264,
                        "fmt": "1.00"
                    }
                }
            ],
            "currentQuarterEstimate": {
                "raw": 1.21808,
                "fmt": "1.22"
            },
            "currentQuarterEstimateDate": "1Q",
            "currentQuarterEstimateYear": 2025,
            "earningsDate": [
                {
                    "raw": 1746561600,
                    "fmt": "2025-05-06"
                }
            ],
            "isEarningsDateEstimate": false
        },
        "financialsChart": {
            "yearly": [
                {
                    "date": 2021,
                    "revenue": {
                        "raw": 12206000000,
                        "fmt": "12.21B",
                        "longFmt": "12,206,000,000"
                    },
                    "earnings": {
                        "raw": 2374000000,
                        "fmt": "2.37B",
                        "longFmt": "2,374,000,000"
                    }
                },
                {
                    "date": 2022,
                    "revenue": {
                        "raw": 19169000000,
                        "fmt": "19.17B",
                        "longFmt": "19,169,000,000"
                    },
                    "earnings": {
                        "raw": 5476000000,
                        "fmt": "5.48B",
                        "longFmt": "5,476,000,000"
                    }
                },
                {
                    "date": 2023,
                    "revenue": {
                        "raw": 15258000000,
                        "fmt": "15.26B",
                        "longFmt": "15,258,000,000"
                    },
                    "earnings": {
                        "raw": 3667000000,
                        "fmt": "3.67B",
                        "longFmt": "3,667,000,000"
                    }
                },
                {
                    "date": 2024,
                    "revenue": {
                        "raw": 15940000000,
                        "fmt": "15.94B",
                        "longFmt": "15,940,000,000"
                    },
                    "earnings": {
                        "raw": 3054000000,
                        "fmt": "3.05B",
                        "longFmt": "3,054,000,000"
                    }
                }
            ],
            "quarterly": [
                {
                    "date": "1Q2024",
                    "revenue": {
                        "raw": 3596000000,
                        "fmt": "3.6B",
                        "longFmt": "3,596,000,000"
                    },
                    "earnings": {
                        "raw": 730000000,
                        "fmt": "730M",
                        "longFmt": "730,000,000"
                    }
                },
                {
                    "date": "2Q2024",
                    "revenue": {
                        "raw": 3917000000,
                        "fmt": "3.92B",
                        "longFmt": "3,917,000,000"
                    },
                    "earnings": {
                        "raw": 885000000,
                        "fmt": "885M",
                        "longFmt": "885,000,000"
                    }
                },
                {
                    "date": "3Q2024",
                    "revenue": {
                        "raw": 4024000000,
                        "fmt": "4.02B",
                        "longFmt": "4,024,000,000"
                    },
                    "earnings": {
                        "raw": 683000000,
                        "fmt": "683M",
                        "longFmt": "683,000,000"
                    }
                },
                {
                    "date": "4Q2024",
                    "revenue": {
                        "raw": 4403000000,
                        "fmt": "4.4B",
                        "longFmt": "4,403,000,000"
                    },
                    "earnings": {
                        "raw": 756000000,
                        "fmt": "756M",
                        "longFmt": "756,000,000"
                    }
                }
            ]
        },
        "financialCurrency": "USD"
    },
    "calendarEvents": {
        "maxAge": 1,
        "earnings": {
            "earningsDate": [
                {
                    "raw": 1746561600,
                    "fmt": "2025-05-06"
                }
            ],
            "earningsCallDate": [
                {
                    "raw": 1746630000,
                    "fmt": "2025-05-07"
                }
            ],
            "isEarningsDateEstimate": false,
            "earningsAverage": {
                "raw": 1.21808,
                "fmt": "1.22"
            },
            "earningsLow": {
                "raw": 0.94,
                "fmt": "0.94"
            },
            "earningsHigh": {
                "raw": 1.35,
                "fmt": "1.35"
            },
            "revenueAverage": {
                "raw": 4372025390,
                "fmt": "4.37B",
                "longFmt": "4,372,025,390"
            },
            "revenueLow": {
                "raw": 4182901350,
                "fmt": "4.18B",
                "longFmt": "4,182,901,350"
            },
            "revenueHigh": {
                "raw": 4587000000,
                "fmt": "4.59B",
                "longFmt": "4,587,000,000"
            }
        },
        "exDividendDate": {
            "raw": 1741910400,
            "fmt": "2025-03-14"
        },
        "dividendDate": {
            "raw": 1743379200,
            "fmt": "2025-03-31"
        }
    },
    "pageViews": {
        "shortTermTrend": "DOWN",
        "midTermTrend": "UP",
        "longTermTrend": "UP",
        "maxAge": 1
    },
    "price": {
        "maxAge": 1,
        "preMarketChange": {},
        "preMarketPrice": {},
        "preMarketSource": "FREE_REALTIME",
        "postMarketChangePercent": {
            "raw": 0.0012837801,
            "fmt": "0.13%"
        },
        "postMarketChange": {
            "raw": 0.0398998,
            "fmt": "0.04"
        },
        "postMarketTime": 1745452655,
        "postMarketPrice": {
            "raw": 31.1199,
            "fmt": "31.12"
        },
        "postMarketSource": "FREE_REALTIME",
        "regularMarketChangePercent": {
            "raw": -0.0038461802,
            "fmt": "-0.38%"
        },
        "regularMarketChange": {
            "raw": -0.120001,
            "fmt": "-0.12"
        },
        "regularMarketTime": 1745438405,
        "priceHint": {
            "raw": 2,
            "fmt": "2",
            "longFmt": "2"
        },
        "regularMarketPrice": {
            "raw": 31.08,
            "fmt": "31.08"
        },
        "regularMarketDayHigh": {
            "raw": 32.31,
            "fmt": "32.31"
        },
        "regularMarketDayLow": {
            "raw": 30.71,
            "fmt": "30.71"
        },
        "regularMarketVolume": {
            "raw": 8068172,
            "fmt": "8.07M",
            "longFmt": "8,068,172.00"
        },
        "averageDailyVolume10Day": {
            "raw": 13249840,
            "fmt": "13.25M",
            "longFmt": "13,249,840"
        },
        "averageDailyVolume3Month": {
            "raw": 10138278,
            "fmt": "10.14M",
            "longFmt": "10,138,278"
        },
        "regularMarketPreviousClose": {
            "raw": 31.2,
            "fmt": "31.20"
        },
        "regularMarketSource": "FREE_REALTIME",
        "regularMarketOpen": {
            "raw": 31.74,
            "fmt": "31.74"
        },
        "strikePrice": {},
        "openInterest": {},
        "exchange": "NYQ",
        "exchangeName": "NYSE",
        "exchangeDataDelayedBy": 0,
        "marketState": "PREPRE",
        "quoteType": "EQUITY",
        "symbol": "DVN",
        "underlyingSymbol": null,
        "shortName": "Devon Energy Corporation",
        "longName": "Devon Energy Corporation",
        "currency": "USD",
        "quoteSourceName": "Nasdaq Real Time Price",
        "currencySymbol": "$",
        "fromCurrency": null,
        "toCurrency": null,
        "lastMarket": null,
        "volume24Hr": {},
        "volumeAllCurrencies": {},
        "circulatingSupply": {},
        "marketCap": {
            "raw": 20157057024,
            "fmt": "20.16B",
            "longFmt": "20,157,057,024.00"
        }
    },
    "corporateActions": {
        "corporateActions": [],
        "maxAge": 1
    },
    "financialData": {
        "maxAge": 86400,
        "currentPrice": {
            "raw": 31.08,
            "fmt": "31.08"
        },
        "targetHighPrice": {
            "raw": 66.0,
            "fmt": "66.00"
        },
        "targetLowPrice": {
            "raw": 32.0,
            "fmt": "32.00"
        },
        "targetMeanPrice": {
            "raw": 44.24148,
            "fmt": "44.24"
        },
        "targetMedianPrice": {
            "raw": 43.0,
            "fmt": "43.00"
        },
        "recommendationMean": {
            "raw": 1.92593,
            "fmt": "1.93"
        },
        "recommendationKey": "buy",
        "numberOfAnalystOpinions": {
            "raw": 27,
            "fmt": "27",
            "longFmt": "27"
        },
        "totalCash": {
            "raw": 811000000,
            "fmt": "811M",
            "longFmt": "811,000,000"
        },
        "totalCashPerShare": {
            "raw": 1.25,
            "fmt": "1.25"
        },
        "ebitda": {
            "raw": 7389000192,
            "fmt": "7.39B",
            "longFmt": "7,389,000,192"
        },
        "totalDebt": {
            "raw": 9255999488,
            "fmt": "9.26B",
            "longFmt": "9,255,999,488"
        },
        "quickRatio": {
            "raw": 0.841,
            "fmt": "0.84"
        },
        "currentRatio": {
            "raw": 1.036,
            "fmt": "1.04"
        },
        "totalRevenue": {
            "raw": 15171000320,
            "fmt": "15.17B",
            "longFmt": "15,171,000,320"
        },
        "debtToEquity": {
            "raw": 62.949,
            "fmt": "62.95%"
        },
        "revenuePerShare": {
            "raw": 24.005,
            "fmt": "24.00"
        },
        "returnOnAssets": {
            "raw": 0.093100004,
            "fmt": "9.31%"
        },
        "returnOnEquity": {
            "raw": 0.21857001,
            "fmt": "21.86%"
        },
        "grossProfits": {
            "raw": 8015000064,
            "fmt": "8.02B",
            "longFmt": "8,015,000,064"
        },
        "freeCashflow": {
            "raw": -1725250048,
            "fmt": "-1.73B",
            "longFmt": "-1,725,250,048"
        },
        "operatingCashflow": {
            "raw": 6600000000,
            "fmt": "6.6B",
            "longFmt": "6,600,000,000"
        },
        "earningsGrowth": {
            "raw": -0.461,
            "fmt": "-46.10%"
        },
        "revenueGrowth": {
            "raw": 0.176,
            "fmt": "17.60%"
        },
        "grossMargins": {
            "raw": 0.52831,
            "fmt": "52.83%"
        },
        "ebitdaMargins": {
            "raw": 0.48705003,
            "fmt": "48.71%"
        },
        "operatingMargins": {
            "raw": 0.22400999,
            "fmt": "22.40%"
        },
        "profitMargins": {
            "raw": 0.19056,
            "fmt": "19.06%"
        },
        "financialCurrency": "USD"
    }
}